domain_email_records/__init__.py
domain_email_records/constants.py
domain_email_records/exceptions.py
domain_email_records/lib/__init__.py
domain_email_records/lib/args.py
domain_email_records/lib/domain_email_records.py
domain_email_records/lib/logger.py
domain_email_records/main.py
domain_email_records/py.typed
domain_email_records-0.5.2.dist-info/LICENSE
domain_email_records-0.5.2.dist-info/METADATA
domain_email_records-0.5.2.dist-info/WHEEL
domain_email_records-0.5.2.dist-info/entry_points.txt
domain_email_records-0.5.2.dist-info/RECORD
