Metadata-Version: 2.1
Name: domain-email-records
Version: 0.5.2
Summary: CLI tool to quickly lookup MX, SPF, DMARC records for many domains
License: BSD-2-Clause
Keywords: domain-name,dns,email,spf,dmarc
Author: Nicholas de Jong
Author-email: ndejong@threatpatrols.com
Requires-Python: >=3.8,<4.0
Classifier: Environment :: Console
Classifier: Intended Audience :: Information Technology
Classifier: Intended Audience :: System Administrators
Classifier: License :: OSI Approved :: BSD License
Classifier: Programming Language :: Python :: 3
Classifier: Programming Language :: Python :: 3.8
Classifier: Programming Language :: Python :: 3.9
Classifier: Programming Language :: Python :: 3.10
Classifier: Programming Language :: Python :: 3.11
Requires-Dist: async_lru (>=2.0,<2.1)
Requires-Dist: dnspython (>=2.4,<2.5)
Project-URL: Bug Tracker, https://github.com/ndejong/domain-email-records/issues
Project-URL: Documentation, https://github.com/ndejong/domain-email-records
Project-URL: Homepage, https://github.com/ndejong/domain-email-records
Project-URL: Repository, https://github.com/ndejong/domain-email-records.git
